langgraph/cache/sqlite/__init__.py
langgraph/checkpoint/sqlite/__init__.py
langgraph/checkpoint/sqlite/aio.py
langgraph/checkpoint/sqlite/py.typed
langgraph/checkpoint/sqlite/utils.py
langgraph/store/sqlite/__init__.py
langgraph/store/sqlite/aio.py
langgraph/store/sqlite/base.py
langgraph_checkpoint_sqlite-2.0.9.dist-info/METADATA
langgraph_checkpoint_sqlite-2.0.9.dist-info/WHEEL
langgraph_checkpoint_sqlite-2.0.9.dist-info/RECORD
