Metadata-Version: 2.4
Name: langgraph-checkpoint-sqlite
Version: 2.0.9
Summary: Library with a SQLite implementation of LangGraph checkpoint saver.
Project-URL: Repository, https://www.github.com/langchain-ai/langgraph
License-Expression: MIT
Requires-Python: >=3.9
Requires-Dist: aiosqlite>=0.20
Requires-Dist: langgraph-checkpoint>=2.0.21
Requires-Dist: sqlite-vec>=0.1.6
